__init__.py
sheetbuddy.py
sheetbuddy-3.1.1.dist-info/LICENSE
sheetbuddy-3.1.1.dist-info/METADATA
sheetbuddy-3.1.1.dist-info/WHEEL
sheetbuddy-3.1.1.dist-info/top_level.txt
sheetbuddy-3.1.1.dist-info/RECORD
