Metadata-Version: 2.1
Name: sheetbuddy
Version: 3.1.1
Summary: A library for data summary and analysis from various formats such as CSV, API, URL, etc.
Home-page: https://github.com/AshishRogannagari/sheetbuddy
Author: Ashish Rogannagari
Author-email: Ashishrogannagari98@gmail.com
Keywords: data analysis,data summary,CSV,API,URL,pandas,requests,openpyxl,tqdm,excel,eda,data,data science,data engineering,data analytics,data visualization,data manipulation,data cleaning,data wrangling,data preprocessing,data transformation,data exploration,data mining,data modeling,data interpretation,data presentation,data reporting,data storytelling
Classifier: Programming Language :: Python :: 3
Classifier: Programming Language :: Python :: 3.7
Classifier: Programming Language :: Python :: 3.8
Classifier: Programming Language :: Python :: 3.9
Classifier: Programming Language :: Python :: 3.10
Classifier: Programming Language :: Python :: 3.11
Classifier: Programming Language :: Python :: 3.12
Classifier: License :: OSI Approved :: MIT License
Classifier: License :: OSI Approved :: MIT License
Classifier: Operating System :: OS Independent
Classifier: Development Status :: 3 - Alpha
Classifier: Intended Audience :: Developers
Classifier: Intended Audience :: Science/Research
Classifier: Intended Audience :: Education
Classifier: Topic :: Scientific/Engineering
Classifier: Topic :: Scientific/Engineering :: Mathematics
Classifier: Topic :: Scientific/Engineering :: Visualization
Classifier: Topic :: Scientific/Engineering :: Information Analysis
Classifier: Topic :: Scientific/Engineering :: Artificial Intelligence
Classifier: Topic :: Software Development
Classifier: Topic :: Software Development :: Libraries
Classifier: Topic :: Software Development :: Libraries :: Python Modules
Classifier: Natural Language :: English
Requires-Python: >=3.7
License-File: LICENSE
Requires-Dist: pandas
Requires-Dist: numpy
Requires-Dist: requests
Requires-Dist: openpyxl
Requires-Dist: tqdm
Requires-Dist: matplotlib
Requires-Dist: seaborn
Requires-Dist: scipy
